[
  {
    "id": "10764272",
    "title": "A close-up of firewood burning with vivid orange flames, sho",
    "url": "https://raw.githubusercontent.com/myhorsevideo1-boop/wallpaper-assets/main/images/fire/01.jpg"
  },
  {
    "id": "4275991",
    "title": "A dramatic fire blazing against the night sky, showing inten",
    "url": "https://raw.githubusercontent.com/myhorsevideo1-boop/wallpaper-assets/main/images/fire/02.jpg"
  },
  {
    "id": "25751684",
    "title": "Close-up of vibrant flames showcasing the dynamic nature of ",
    "url": "https://raw.githubusercontent.com/myhorsevideo1-boop/wallpaper-assets/main/images/fire/03.jpg"
  },
  {
    "id": "18561037",
    "title": "A mesmerizing view of vibrant flames dancing over logs in a ",
    "url": "https://raw.githubusercontent.com/myhorsevideo1-boop/wallpaper-assets/main/images/fire/04.jpg"
  },
  {
    "id": "34648346",
    "title": "Dramatic close-up of flames against a dark background, highl",
    "url": "https://raw.githubusercontent.com/myhorsevideo1-boop/wallpaper-assets/main/images/fire/05.jpg"
  },
  {
    "id": "20408513",
    "title": "Captivating image of swirling flames against a dark backdrop",
    "url": "https://raw.githubusercontent.com/myhorsevideo1-boop/wallpaper-assets/main/images/fire/06.jpg"
  },
  {
    "id": "17356413",
    "title": "A close-up of bright flames with a warm glow, set against a ",
    "url": "https://raw.githubusercontent.com/myhorsevideo1-boop/wallpaper-assets/main/images/fire/07.jpg"
  },
  {
    "id": "26986693",
    "title": "Dramatic close-up capture of flames dancing at night with vi",
    "url": "https://raw.githubusercontent.com/myhorsevideo1-boop/wallpaper-assets/main/images/fire/08.jpg"
  },
  {
    "id": "26986698",
    "title": "A vibrant campfire with flickering flames set against a dark",
    "url": "https://raw.githubusercontent.com/myhorsevideo1-boop/wallpaper-assets/main/images/fire/09.jpg"
  },
  {
    "id": "12264029",
    "title": "Dramatic capture of flickering flames with vivid orange hues",
    "url": "https://raw.githubusercontent.com/myhorsevideo1-boop/wallpaper-assets/main/images/fire/10.jpg"
  },
  {
    "id": "15129753",
    "title": "A captivating view of flames dancing in the dark, showcasing",
    "url": "https://raw.githubusercontent.com/myhorsevideo1-boop/wallpaper-assets/main/images/fire/11.jpg"
  },
  {
    "id": "17143428",
    "title": "Close-up of vibrant fires flames on black background creatin",
    "url": "https://raw.githubusercontent.com/myhorsevideo1-boop/wallpaper-assets/main/images/fire/12.jpg"
  },
  {
    "id": "14288953",
    "title": "Vibrant flames rising from a campfire, creating mesmerizing ",
    "url": "https://raw.githubusercontent.com/myhorsevideo1-boop/wallpaper-assets/main/images/fire/13.jpg"
  },
  {
    "id": "11679667",
    "title": "Captivating close-up of vibrant flames against a dark backgr",
    "url": "https://raw.githubusercontent.com/myhorsevideo1-boop/wallpaper-assets/main/images/fire/14.jpg"
  },
  {
    "id": "28295909",
    "title": "Dynamic and vivid flames creating a captivating display agai",
    "url": "https://raw.githubusercontent.com/myhorsevideo1-boop/wallpaper-assets/main/images/fire/15.jpg"
  },
  {
    "id": "15129794",
    "title": "Intense close-up of vibrant flames dancing on a dark backgro",
    "url": "https://raw.githubusercontent.com/myhorsevideo1-boop/wallpaper-assets/main/images/fire/16.jpg"
  },
  {
    "id": "15129795",
    "title": "Captivating image of swirling flames against a dark backgrou",
    "url": "https://raw.githubusercontent.com/myhorsevideo1-boop/wallpaper-assets/main/images/fire/17.jpg"
  },
  {
    "id": "26986692",
    "title": "Intense flames dance in a nighttime bonfire, creating a dram",
    "url": "https://raw.githubusercontent.com/myhorsevideo1-boop/wallpaper-assets/main/images/fire/18.jpg"
  },
  {
    "id": "15129796",
    "title": "Vivid flames dance in a bonfire against a dark night sky, cr",
    "url": "https://raw.githubusercontent.com/myhorsevideo1-boop/wallpaper-assets/main/images/fire/19.jpg"
  },
  {
    "id": "29536721",
    "title": "Warm and vibrant fire flames captured at night, providing a ",
    "url": "https://raw.githubusercontent.com/myhorsevideo1-boop/wallpaper-assets/main/images/fire/20.jpg"
  }
]